nextstep_plist/__init__.py
nextstep_plist/decoder.py
nextstep_plist/scanner.py
nextstep_plist-0.1.0.dist-info/DESCRIPTION.rst
nextstep_plist-0.1.0.dist-info/METADATA
nextstep_plist-0.1.0.dist-info/RECORD
nextstep_plist-0.1.0.dist-info/WHEEL
nextstep_plist-0.1.0.dist-info/metadata.json
nextstep_plist-0.1.0.dist-info/top_level.txt
